kerdosai/__init__.py
kerdosai/agent.py
kerdosai/deployer.py
kerdosai/processor.py
kerdosai/trainer.py
kerdosai-0.1.1.dist-info/METADATA
kerdosai-0.1.1.dist-info/WHEEL
kerdosai-0.1.1.dist-info/top_level.txt
kerdosai-0.1.1.dist-info/RECORD
