Metadata-Version: 2.4
Name: kerdosai
Version: 0.1.1
Summary: Universal LLM Training Agent
Home-page: https://kerdos.in
Author: KerdosAI Team
Author-email: support@kerdos.in
Project-URL: Homepage, https://kerdos.in
Project-URL: Documentation, https://kerdos.in/docs
Project-URL: Support, https://kerdos.in/support
Project-URL: Bug Tracker, https://kerdos.in/issues
Classifier: Development Status :: 3 - Alpha
Classifier: Intended Audience :: Developers
Classifier: License :: OSI Approved :: MIT License
Classifier: Programming Language :: Python :: 3
Classifier: Programming Language :: Python :: 3.8
Classifier: Programming Language :: Python :: 3.9
Classifier: Programming Language :: Python :: 3.10
Classifier: Programming Language :: Python :: 3.11
Requires-Python: >=3.8
Requires-Dist: torch>=2.0.0
Requires-Dist: transformers>=4.30.0
Requires-Dist: numpy>=1.24.0
Requires-Dist: pandas>=2.0.0
Requires-Dist: scikit-learn>=1.0.0
Requires-Dist: tqdm>=4.65.0
Dynamic: author
Dynamic: author-email
Dynamic: classifier
Dynamic: description
Dynamic: description-content-type
Dynamic: home-page
Dynamic: project-url
Dynamic: requires-dist
Dynamic: requires-python
Dynamic: summary
